Metadata-Version: 2.1
Name: bookit
Version: 0.0.5
Summary: Doc site generator
Home-page: https://github.com/agmoss/bookit
Author: Andrew Moss
Author-email: andrew@m0ss.dev
License: MIT license
Platform: UNKNOWN
Classifier: Development Status :: 3 - Alpha
Classifier: Intended Audience :: Developers
Classifier: License :: OSI Approved :: MIT License
Classifier: Natural Language :: English
Classifier: Programming Language :: Python :: 3
Requires-Python: >=3.7
License-File: LICENSE
